credmark/client/__init__.py
credmark/client/cli.py
credmark/client/errors.py
credmark/client/dto/dto_error_schema.py
credmark/client/dto/dto_schema.py
examples/run.py
credmark_client-0.0.1.dist-info/LICENSE
credmark_client-0.0.1.dist-info/METADATA
credmark_client-0.0.1.dist-info/WHEEL
credmark_client-0.0.1.dist-info/entry_points.txt
credmark_client-0.0.1.dist-info/top_level.txt
credmark_client-0.0.1.dist-info/RECORD
