Metadata-Version: 2.1
Name: credmark-client
Version: 0.0.1
Summary: Credmark client lib
Home-page: https://github.com/credmark/credmark-client-py
Author: Credmark
Author-email: info@credmark.com
License: MIT
Keywords: Credmark crypto risk model client
Platform: UNKNOWN
Classifier: Development Status :: 4 - Beta
Classifier: Intended Audience :: Developers
Classifier: License :: OSI Approved :: MIT License
Classifier: Natural Language :: English
Classifier: Programming Language :: Python :: 3
Requires-Python: >=3.7.0
License-File: LICENSE
Requires-Dist: requests (>=2.27.1)
